odoo9_addon_sale_force_invoiced-9.0.1.0.0-py2.7-nspkg.pth
odoo9_addon_sale_force_invoiced-9.0.1.0.0.dist-info/DESCRIPTION.rst
odoo9_addon_sale_force_invoiced-9.0.1.0.0.dist-info/METADATA
odoo9_addon_sale_force_invoiced-9.0.1.0.0.dist-info/RECORD
odoo9_addon_sale_force_invoiced-9.0.1.0.0.dist-info/WHEEL
odoo9_addon_sale_force_invoiced-9.0.1.0.0.dist-info/metadata.json
odoo9_addon_sale_force_invoiced-9.0.1.0.0.dist-info/namespace_packages.txt
odoo9_addon_sale_force_invoiced-9.0.1.0.0.dist-info/top_level.txt
odoo_addons/sale_force_invoiced/README.rst
odoo_addons/sale_force_invoiced/__init__.py
odoo_addons/sale_force_invoiced/__openerp__.py
odoo_addons/sale_force_invoiced/model/__init__.py
odoo_addons/sale_force_invoiced/model/sale_order.py
odoo_addons/sale_force_invoiced/static/description/icon.png
odoo_addons/sale_force_invoiced/tests/__init__.py
odoo_addons/sale_force_invoiced/tests/test_sale_force_invoiced.py
odoo_addons/sale_force_invoiced/view/sale_view.xml
